pyswip_alt-0.2.3.dist-info/DESCRIPTION.rst
pyswip_alt-0.2.3.dist-info/WHEEL
pyswip_alt-0.2.3.dist-info/RECORD
pyswip_alt-0.2.3.dist-info/METADATA
pyswip_alt-0.2.3.dist-info/metadata.json
pyswip_alt-0.2.3.dist-info/top_level.txt
pyswip/prolog.py
pyswip/__init__.py
pyswip/easy.py
pyswip/core.py
