Metadata-Version: 2.0
Name: pyswip-alt
Version: 0.2.3
Summary: PySWIP enables querying SWI-Prolog in your Python programs.
Home-page: https://github.com/JoaoFelipe/pyswip/
Author: Yuce Tekol
Author-email: yucetekol@gmail.com
License: MIT
Platform: UNKNOWN
Classifier: Development Status :: 3 - Alpha
Classifier: Intended Audience :: Developers
Classifier: Intended Audience :: Science/Research
Classifier: Operating System :: OS Independent
Classifier: Programming Language :: Python
Classifier: Topic :: Scientific/Engineering :: Artificial Intelligence
Classifier: Topic :: Software Development :: Libraries :: Python Modules
